markdown_grids/__about__.py
markdown_grids/__init__.py
markdown_grids-1.0.0.dist-info/METADATA
markdown_grids-1.0.0.dist-info/WHEEL
markdown_grids-1.0.0.dist-info/entry_points.txt
markdown_grids-1.0.0.dist-info/licenses/LICENCE.txt
markdown_grids-1.0.0.dist-info/RECORD
