Metadata-Version: 2.1
Name: markdown-grids
Version: 1.0.0
Summary: A Python-Markdown extension to render grid tables
Project-URL: Documentation, https://github.com/mjayfrancis/markdown-grids#readme
Project-URL: Issues, https://github.com/mjayfrancis/markdown-grids/issues
Project-URL: Source, https://github.com/mjayfrancis/markdown-grids
Author-email: Matthew Francis <mjay.francis@gmail.com>
License-Expression: MIT
License-File: LICENCE.txt
Classifier: Development Status :: 4 - Beta
Classifier: Programming Language :: Python
Classifier: Programming Language :: Python :: 3.8
Classifier: Programming Language :: Python :: 3.9
Classifier: Programming Language :: Python :: 3.10
Classifier: Programming Language :: Python :: 3.11
Classifier: Programming Language :: Python :: Implementation :: CPython
Classifier: Programming Language :: Python :: Implementation :: PyPy
Requires-Python: >=3.8
Requires-Dist: markdown>=3.0.0
